aware_terminal/__init__.py
aware_terminal/bindings.py
aware_terminal/cli.py
aware_terminal/metadata.py
aware_terminal/bootstrap/__init__.py
aware_terminal/bootstrap/control.py
aware_terminal/bootstrap/gnome.py
aware_terminal/bootstrap/launcher.py
aware_terminal/bootstrap/systemd.py
aware_terminal/bootstrap/tmux.py
aware_terminal/bootstrap/tmux_service.py
aware_terminal/bootstrap/window_manager/__init__.py
aware_terminal/bootstrap/window_manager/base.py
aware_terminal/bootstrap/window_manager/gnome.py
aware_terminal/bootstrap/window_manager/layouts.py
aware_terminal/control_center/__init__.py
aware_terminal/control_center/mock_provider.py
aware_terminal/control_center/models.py
aware_terminal/control_center/provider.py
aware_terminal/control_center/view_model.py
aware_terminal/control_center/layout/__init__.py
aware_terminal/control_center/layout/components.py
aware_terminal/control_center/layout/markdown_view.py
aware_terminal/control_center/layout/renderer.py
aware_terminal/control_center/layout/status_panel.py
aware_terminal/core/config.py
aware_terminal/core/config_store.py
aware_terminal/core/env.py
aware_terminal/core/installers.py
aware_terminal/core/util.py
aware_terminal/daemon/__init__.py
aware_terminal/daemon/client.py
aware_terminal/daemon/ipc.py
aware_terminal/daemon/manifest.py
aware_terminal/daemon/models.py
aware_terminal/daemon/paths.py
aware_terminal/daemon/server.py
aware_terminal/daemon/session_manager.py
aware_terminal/doctor/__init__.py
aware_terminal/doctor/context.py
aware_terminal/doctor/models.py
aware_terminal/doctor/runner.py
aware_terminal/doctor/checks/__init__.py
aware_terminal/doctor/checks/environment.py
aware_terminal/doctor/checks/gnome.py
aware_terminal/doctor/checks/providers.py
aware_terminal/doctor/checks/terminals.py
aware_terminal/doctor/checks/tmux.py
aware_terminal/doctor/renderers/__init__.py
aware_terminal/doctor/renderers/text.py
aware_terminal/integrations/bindings.py
aware_terminal/mock_data/bindings.json
aware_terminal-0.3.3.dist-info/METADATA
aware_terminal-0.3.3.dist-info/WHEEL
aware_terminal-0.3.3.dist-info/entry_points.txt
aware_terminal-0.3.3.dist-info/licenses/LICENSE
aware_terminal-0.3.3.dist-info/RECORD
